AUTHORS.rst
CONTRIBUTING.rst
HISTORY.rst
LICENSE
MANIFEST.in
README.rst
pyproject.toml
setup.cfg
setup.py
Django_clear_s2s.egg-info/PKG-INFO
Django_clear_s2s.egg-info/SOURCES.txt
Django_clear_s2s.egg-info/dependency_links.txt
Django_clear_s2s.egg-info/not-zip-safe
Django_clear_s2s.egg-info/requires.txt
Django_clear_s2s.egg-info/top_level.txt
django_clear_s2s/__init__.py
django_clear_s2s/admin.py
django_clear_s2s/apps.py
django_clear_s2s/models.py
django_clear_s2s/urls.py
django_clear_s2s/views.py
django_clear_s2s/static/css/django_clear_s2s.css
django_clear_s2s/static/js/django_clear_s2s.js
django_clear_s2s/templates/django_clear_s2s/BusinessSearchRequest.xml
django_clear_s2s/templates/django_clear_s2s/CompanyQuickAnalysisFlagRequest.xml
django_clear_s2s/templates/django_clear_s2s/EIDVPersonSearch.xml
django_clear_s2s/templates/django_clear_s2s/PersonQuickAnalysisFlagRequest.xml
django_clear_s2s/templates/django_clear_s2s/PersonSearchRequest.xml
django_clear_s2s/templates/django_clear_s2s/WebAndSocialMediaSearchRequest.xml
django_clear_s2s/templates/django_clear_s2s/base.html
django_clear_s2s/test_utils/__init__.py
django_clear_s2s/test_utils/test_app/__init__.py
django_clear_s2s/test_utils/test_app/admin.py
django_clear_s2s/test_utils/test_app/apps.py
django_clear_s2s/test_utils/test_app/models.py
django_clear_s2s/test_utils/test_app/migrations/__init__.py
django_clear_s2s/utils/ThomsonReuters.py
django_clear_s2s/utils/exceptions.py