Metadata-Version: 2.1
Name: Django-clear-s2s
Version: 0.1.5
Summary: Django Extension for Clear S2S
Home-page: https://github.com/sal-git/Django-clear-s2s
Author: Stephen Lightcap
Author-email: stephen@lightcap.net
License: BSD
Keywords: Django-clear-s2s
Platform: UNKNOWN
Classifier: Development Status :: 3 - Alpha
Classifier: Framework :: Django
Classifier: Intended Audience :: Developers
Classifier: License :: OSI Approved :: BSD License
Classifier: Natural Language :: English
Classifier: Programming Language :: Python :: 3
Classifier: Programming Language :: Python :: 3.5
Classifier: Programming Language :: Python :: 3.6
License-File: LICENSE
License-File: AUTHORS.rst
